pan_valid/__init__.py
pan_valid-0.1.dist-info/LICENCE.txt
pan_valid-0.1.dist-info/METADATA
pan_valid-0.1.dist-info/WHEEL
pan_valid-0.1.dist-info/top_level.txt
pan_valid-0.1.dist-info/RECORD
