Metadata-Version: 2.1
Name: pan_valid
Version: 0.1
Summary: This package will help you to findout pan number is valid or not
Author: Saral Kumar Kaviti
Author-email: saralkumar.kapilit@gmail.com
Classifier: Programming Language :: Python :: 3
Classifier: License :: OSI Approved :: MIT License
Classifier: Operating System :: OS Independent
License-File: LICENCE.txt
